./Dockerfile
./LICENSE
./PKG-INFO
./README.md
./inject_bender_server.py
./pyproject.toml
./test_bender.py
mcp_server_inject_bender-1.1.0.dist-info/METADATA
mcp_server_inject_bender-1.1.0.dist-info/WHEEL
mcp_server_inject_bender-1.1.0.dist-info/entry_points.txt
mcp_server_inject_bender-1.1.0.dist-info/licenses/LICENSE
mcp_server_inject_bender-1.1.0.dist-info/RECORD
