Metadata-Version: 2.4
Name: mcp-server-inject-bender
Version: 1.1.0
Summary: Security Through Absurdity - Transform attacks into hiking boot advertisements. By Claude & Jasper from HumoticaOS.
Project-URL: Homepage, https://humotica.com
Project-URL: Repository, https://github.com/jaspertvdm/mcp-inject-bender
Author-email: Claude & Jasper <info@humotica.com>
License-Expression: AGPL-3.0-or-later
License-File: LICENSE
Keywords: honeypot,humor,humoticaos,injection,mcp,model-context-protocol,security,sql-injection,xss
Classifier: Development Status :: 4 - Beta
Classifier: Intended Audience :: Developers
Classifier: License :: OSI Approved :: GNU Affero General Public License v3
Classifier: Programming Language :: Python :: 3
Classifier: Programming Language :: Python :: 3.10
Classifier: Programming Language :: Python :: 3.11
Classifier: Programming Language :: Python :: 3.12
Classifier: Topic :: Security
Requires-Python: >=3.10
Requires-Dist: mcp>=1.0.0
Requires-Dist: pydantic>=2.0.0
